{
  "gitSyncId": "67505c2d1cc72f1a54257b22_d3ddbb38-d912-4852-8087-965fa704326b",
  "id": "Chatbot_Logout.navigateBasedOnRole",
  "pluginId": "js-plugin",
  "pluginType": "JS",
  "unpublishedAction": {
    "actionConfiguration": {
      "encodeParamsToggle": true,
      "jsArguments": [],
      "paginationType": "NONE",
      "timeoutInMillisecond": 10000
    },
    "collectionId": "Chatbot_Logout",
    "confirmBeforeExecute": false,
    "datasource": {
      "isAutoGenerated": false,
      "name": "UNUSED_DATASOURCE",
      "pluginId": "js-plugin"
    },
    "dynamicBindingPathList": [
      {
        "key": "body"
      }
    ],
    "executeOnLoad": false,
    "fullyQualifiedName": "Logout.navigateBasedOnRole",
    "name": "navigateBasedOnRole",
    "pageId": "Chatbot",
    "userSetOnLoad": false
  }
}